py_draw/__init__.py
py_draw-0.0.8.dist-info/METADATA
py_draw-0.0.8.dist-info/WHEEL
py_draw-0.0.8.dist-info/entry_points.txt
py_draw-0.0.8.dist-info/top_level.txt
py_draw-0.0.8.dist-info/RECORD
